{
    "page 1": {
        "item Name": [
            "Mi 3i 10000 mAh Power Bank (Fast Charging, 18W)",
            "Cellecor 10000 mAh Power Bank (12 W, Fast Charging)",
            "Mi 3i 20000 mAh Power Bank (Fast Charging, 18W)",
            "Mi 3i 10000 mAh Power Bank (Fast Charging, 18W)",
            "Mi 10000 mAh Power Bank (22.5 W, Fast Charging)",
            "Ambrane 10000 mAh Power Bank (12 W, Fast Charging)",
            "Ambrane 10000 mAh Power Bank (12 W, Fast Charging)",
            "Ambrane 20000 mAh Power Bank (20 W, Power Delivery 3.0,...",
            "Mi 30000 mAh Power Bank (18 W, Fast Charging, Power Del...",
            "ORAIMO 20000 mAh Power Bank (12 w, Fast Charging)",
            "URBN 20000 mAh Power Bank (12 W)",
            "URBN 20000 mAh Power Bank (12 W)",
            "ORAIMO 20000 mAh Power Bank (12 w, Fast Charging)",
            "boAt 20000 mAh Power Bank (22.5 W, Quick Charge 3.0)",
            "boAt 20000 mAh Power Bank (22.5 W, Quick Charge 3.0)",
            "boAt 20000 mAh Power Bank (22.5 W, Quick Charge 3.0)",
            "URBN 10000 mAh Power Bank (12 W)",
            "URBN 10000 mAh Power Bank (12 W)",
            "boAt 20000 mAh Power Bank (22.5 W, Quick Charge 3.0)",
            "REDMI 20000 mAh Power Bank (18 W, Fast Charging)",
            "URBN 10000 mAh Power Bank (12 W)",
            "URBN 10000 mAh Power Bank (12 W)",
            "REDMI 20000 mAh Power Bank (18 W, Fast Charging)",
            "REDMI 10000 mAh Power Bank (10 W, Fast Charging)",
            "Ambrane 20000 mAh Power Bank (20 W, Power Delivery 3.0,...",
            "Ambrane 20000 mAh Power Bank (20 W, Power Delivery 3.0,...",
            "Cellecor 10000 mAh Power Bank (10 W, Fast Charging)",
            "TEMPT 10000 mAh Power Bank (12 W, Fast Charging)",
            "REDMI 10000 mAh Power Bank (10 W, Fast Charging)",
            "Ambrane 20000 mAh Power Bank (22.5 W, Fast Charging)",
            "Cellecor 10000 mAh Power Bank (12 W, Fast Charging)",
            "TEMPT 10000 mAh Power Bank (12 W, Fast Charging)",
            "boAt 10000 mAh Wireless Power Bank (22.5 W, Quick Charg...",
            "Ambrane 10000 mAh Power Bank (20 W, Quick Charge 3.0, P...",
            "Ambrane 10000 mAh Power Bank (20 W, Quick Charge 3.0, P...",
            "Ambrane 10000 mAh Power Bank (20 W, Quick Charge 3.0, P...",
            "ORAIMO 10000 mAh Power Bank (12 W, Fast Charging)",
            "ORAIMO 20000 mAh Power Bank (20 w, Quick Charge 3.0, Po...",
            "boAt 10000 mAh Power Bank (22.5 W, Quick Charge 3.0)",
            "boAt 10000 mAh Power Bank (22.5 W, Quick Charge 3.0)",
            "",
            "",
            "",
            ""
        ],
        "Item Price": [
            "\u20b91,149",
            "\u20b9752",
            "\u20b91,899",
            "\u20b91,149",
            "\u20b91,599",
            "\u20b9799",
            "\u20b9799",
            "\u20b91,599",
            "\u20b93,199",
            "\u20b9899",
            "\u20b91,299",
            "\u20b91,299",
            "\u20b9899",
            "\u20b91,599",
            "\u20b91,599",
            "\u20b91,599",
            "\u20b9899",
            "\u20b9899",
            "\u20b91,599",
            "\u20b91,799",
            "\u20b9899",
            "\u20b9899",
            "\u20b91,799",
            "\u20b91,049",
            "\u20b91,599",
            "\u20b91,599",
            "\u20b91,079",
            "\u20b9949",
            "\u20b91,049",
            "\u20b91,999",
            "\u20b9829",
            "\u20b9949",
            "\u20b91,599",
            "\u20b9899",
            "\u20b9899",
            "\u20b9899",
            "\u20b9699",
            "\u20b91,299",
            "\u20b91,099",
            "\u20b9999",
            "",
            "",
            "",
            ""
        ],
        "Item MRP": [
            "\u20b92,199",
            "\u20b91,999",
            "\u20b92,199",
            "\u20b92,199",
            "\u20b92,699",
            "\u20b91,499",
            "\u20b91,499",
            "\u20b92,499",
            "\u20b94,999",
            "\u20b92,499",
            "\u20b93,499",
            "\u20b93,499",
            "\u20b92,499",
            "\u20b94,499",
            "\u20b94,499",
            "\u20b94,499",
            "\u20b92,499",
            "\u20b92,499",
            "\u20b94,499",
            "\u20b93,199",
            "\u20b92,499",
            "\u20b92,499",
            "\u20b92,999",
            "\u20b91,999",
            "\u20b92,499",
            "\u20b92,499",
            "\u20b92,999",
            "\u20b91,999",
            "\u20b91,999",
            "\u20b93,999",
            "\u20b91,999",
            "\u20b91,999",
            "\u20b93,499",
            "\u20b91,599",
            "\u20b91,599",
            "\u20b91,499",
            "\u20b91,699",
            "\u20b92,999",
            "\u20b92,999",
            "\u20b92,999",
            "",
            "",
            "",
            ""
        ],
        "Item Discount": [
            "47% off",
            "62% off",
            "13% off",
            "47% off",
            "40% off",
            "46% off",
            "46% off",
            "36% off",
            "36% off",
            "64% off",
            "62% off",
            "62% off",
            "64% off",
            "64% off",
            "64% off",
            "64% off",
            "64% off",
            "64% off",
            "64% off",
            "43% off",
            "64% off",
            "64% off",
            "40% off",
            "47% off",
            "36% off",
            "36% off",
            "64% off",
            "52% off",
            "47% off",
            "50% off",
            "58% off",
            "52% off",
            "54% off",
            "43% off",
            "43% off",
            "40% off",
            "58% off",
            "56% off",
            "63% off",
            "66% off",
            "",
            "",
            "",
            ""
        ],
        "Item Rating": [
            "4.3",
            "3.6",
            "",
            "",
            "",
            "",
            "",
            "4.2",
            "",
            "",
            "",
            "",
            "",
            "",
            "",
            "",
            "",
            "",
            "",
            "",
            "",
            "",
            "",
            "",
            "",
            "",
            "3.9",
            "4.2",
            "",
            "",
            "3.6",
            "4.2",
            "",
            "",
            "",
            "",
            "",
            "",
            "",
            "",
            "",
            "",
            "",
            ""
        ],
        "No. People rated": [
            "(3,60,384)",
            "(197)",
            "",
            "",
            "",
            "",
            "",
            "(30,015)",
            "",
            "",
            "",
            "",
            "",
            "",
            "",
            "",
            "",
            "",
            "",
            "",
            "",
            "",
            "",
            "",
            "",
            "",
            "(39)",
            "(70)",
            "",
            "",
            "(197)",
            "(70)",
            "",
            "",
            "",
            "",
            "",
            "",
            "",
            "",
            "",
            "",
            "",
            ""
        ]
    }
}